{
	"$NodeId":	"PropDistributionAlgo.GridWave-6400ed3a-ec58-44c6-8952-b869387458f4",
	"Type":	"PropDistributionAlgo",
	"ExportAs":	"Venice",
	"Skip":	false,
	"GridPoints":	{
		"$NodeId":	"GridGen2D.GridWave-b837b252-0a0f-4252-93bc-dd79391e9e31",
		"Type":	"GridGen2D",
		"Position":	{
			"$NodeId":	"Point3D-92f1f280-232b-447e-ba5f-1e4fb539176a",
			"X":	0,
			"Y":	50,
			"Z":	0
		},
		"OffsetX":	12,
		"OffsetZ":	12,
		"RepeatX":	20,
		"RepeatZ":	20,
		"Centered":	true
	},
	"BaseTiles":	[{
			"$NodeId":	"Single.TileSet.GridWave-b79bb929-b096-4a87-afa0-254269cf7949",
			"Type":	"Single",
			"RuleSet":	{
				"$NodeId":	"Advanced.RuleSet.GridWave-80fda073-db6e-4c18-a539-a0d0e414ddaf",
				"Type":	"Advanced",
				"Provider RuleSets":	{
					"N":	"1",
					"E":	"00",
					"S":	"1",
					"W":	"00"
				},
				"Receiver RuleSets":	{
					"N":	"2",
					"E":	"0,00",
					"S":	"2",
					"W":	"0,00"
				}
			},
			"Weight":	5,
			"MinimizeVariants":	true
		}, {
			"$NodeId":	"Single.TileSet.GridWave-dc330ec6-9343-455f-b5e8-f7383f50a3dd",
			"Type":	"Single",
			"RuleSet":	{
				"$NodeId":	"Advanced.RuleSet.GridWave-6a4b32f0-5091-400c-bae3-84546c715b01",
				"Type":	"Advanced",
				"Provider RuleSets":	{
					"N":	"1",
					"E":	"1",
					"S":	"0",
					"W":	"0"
				},
				"Receiver RuleSets":	{
					"N":	"2",
					"E":	"2",
					"S":	"00",
					"W":	"00"
				}
			},
			"Weight":	0.8,
			"MinimizeVariants":	true
		}, {
			"$NodeId":	"Single.TileSet.GridWave-36262ef1-a7b1-45a0-ae22-58a5d24276f7",
			"Type":	"Single",
			"RuleSet":	{
				"$NodeId":	"Advanced.RuleSet.GridWave-b54237f7-5ab0-4b24-af1c-0ade66cff3f4",
				"Type":	"Advanced",
				"Provider RuleSets":	{
					"N":	"1",
					"E":	"0",
					"S":	"0",
					"W":	"0"
				},
				"Receiver RuleSets":	{
					"N":	"2",
					"E":	"00",
					"S":	"00",
					"W":	"00"
				}
			},
			"Weight":	1,
			"MinimizeVariants":	true
		}, {
			"$NodeId":	"Single.TileSet.GridWave-9b1ec876-2526-4a6e-b65d-d6641ee110d8",
			"Type":	"Single",
			"RuleSet":	{
				"$NodeId":	"Advanced.RuleSet.GridWave-59af98ca-9117-45ec-94a6-062194bda4c1",
				"Type":	"Advanced",
				"Provider RuleSets":	{
					"N":	"2",
					"E":	"2",
					"S":	"2",
					"W":	"2"
				},
				"Receiver RuleSets":	{
					"N":	"2,1",
					"E":	"2,1",
					"S":	"2,1",
					"W":	"2,1"
				}
			},
			"Weight":	0.5,
			"MinimizeVariants":	true
		}],
	"FancyTiles":	[{
			"$NodeId":	"Prop.TileSet.GridWave-b0597374-b0d9-4a94-89e5-a008f277e920",
			"Type":	"Prop",
			"RuleSets":	[{
					"$NodeId":	"Simple.RuleSet.GridWave-e13c314f-02a0-49d7-ade6-c964f5f56277",
					"Type":	"Simple",
					"RuleSet":	{
						"N":	"2",
						"E":	"2"
					}
				}, {
					"$NodeId":	"Simple.RuleSet.GridWave-e3efd51b-7049-4931-a658-bdb3cd3fde74",
					"Type":	"Simple",
					"RuleSet":	{
						"E":	"2",
						"S":	"2"
					}
				}, {
					"$NodeId":	"Simple.RuleSet.GridWave-8a030e79-eb58-417e-84e4-c30743151ba0",
					"Type":	"Simple",
					"RuleSet":	{
						"N":	"2",
						"W":	"2"
					}
				}, {
					"$NodeId":	"Simple.RuleSet.GridWave-3302e4a9-521a-487b-8f1d-f0b53ee78313",
					"Type":	"Simple",
					"RuleSet":	{
						"S":	"2",
						"W":	"2"
					}
				}],
			"Prop":	{
				"$NodeId":	"Union.Prop-6a9e5209-0c90-4b93-943c-c593c1cb0710",
				"Type":	"Union",
				"Skip":	false,
				"Props":	[{
						"$NodeId":	"Prefab.Prop-3d9ce3eb-6e19-48b0-aa46-532388f37f0e",
						"Type":	"Prefab",
						"Skip":	false,
						"WeightedPrefabPaths":	[{
								"$NodeId":	"WeightedPath.Prefab.Prop-d1d1e7a5-5ed7-42b2-aa2b-4725caad61e7",
								"Path":	"FancyTiles/2x2/22XX-X22X-2XX2-XX22",
								"Weight":	1
							}],
						"LegacyPath":	false,
						"LoadEntities":	true,
						"MoldingDirection":	"NONE",
						"MoldingChildren":	false
					}, {
						"$NodeId":	"Prefab.Prop-66811315-d9d1-4312-bfda-86190cf40fc2",
						"Type":	"Prefab",
						"Skip":	false,
						"WeightedPrefabPaths":	[{
								"$NodeId":	"WeightedPath.Prefab.Prop-75501c38-3428-47a0-8a51-1c94d93f2390",
								"Path":	"BaseTiles/Foundations/Full2x2",
								"Weight":	1
							}],
						"LegacyPath":	false,
						"LoadEntities":	true,
						"MoldingDirection":	"NONE",
						"MoldingChildren":	false
					}]
			},
			"SizeZ":	2,
			"Weight":	1
		}, {
			"$NodeId":	"Prop.TileSet.GridWave-4b63bc27-28e4-478e-bbc0-94058954d56e",
			"Type":	"Prop",
			"RuleSets":	[{
					"$NodeId":	"Simple.RuleSet.GridWave-812619e0-dd3b-4134-b43d-3a7723a0197f",
					"Type":	"Simple",
					"RuleSet":	{
						"N":	"2",
						"E":	"2",
						"S":	"2",
						"W":	"2"
					}
				}],
			"Prop":	{
				"$NodeId":	"Union.Prop-1e61d380-0e40-4f03-9d35-ac2d1ce1566a",
				"Type":	"Union",
				"Skip":	false,
				"Props":	[{
						"$NodeId":	"Prefab.Prop-5a1dbf1f-3b50-4146-915c-8a7db784d841",
						"Type":	"Prefab",
						"Skip":	false,
						"WeightedPrefabPaths":	[{
								"$NodeId":	"WeightedPath.Prefab.Prop-ee82d094-3185-4119-8fce-7b144efe4581",
								"Path":	"BaseTiles/Buildings/1x1/2222",
								"Weight":	1
							}],
						"LegacyPath":	false,
						"LoadEntities":	true,
						"MoldingDirection":	"NONE",
						"MoldingChildren":	false
					}, {
						"$NodeId":	"Prefab.Prop-4523d305-9457-4f87-9d60-64ca7be9db0d",
						"Type":	"Prefab",
						"Skip":	false,
						"WeightedPrefabPaths":	[{
								"$NodeId":	"WeightedPath.Prefab.Prop-584b3acc-2bf5-4cc4-a956-acfbb905dcff",
								"Path":	"BaseTiles/Foundations/Full1x1",
								"Weight":	1
							}],
						"LegacyPath":	false,
						"LoadEntities":	true,
						"MoldingDirection":	"NONE",
						"MoldingChildren":	false
					}]
			},
			"SizeZ":	1,
			"Weight":	1
		}],
	"Seed":	{
		"$NodeId":	"Constant.Seed.GridWave-150a2fbf-b9d0-4a9b-a293-d84e9d8fef96",
		"Type":	"Constant",
		"Seed":	"SomeSeedsssss"
	},
	"Features":	[{
			"$NodeId":	"MultiAttempt.Feature.GridWave-6c4f5e0b-4807-4c7b-9b5f-04314552436f",
			"Type":	"MultiAttempt",
			"Skip":	false,
			"MaxBacktracks":	10000,
			"MaxAttempts":	2000
		}],
	"MaxPositionsCount":	20000,
	"$NodeEditorMetadata":	{
		"$Nodes":	{
			"PropDistributionAlgo.GridWave-6400ed3a-ec58-44c6-8952-b869387458f4":	{
				"$Position":	{
					"$x":	1591,
					"$y":	491
				},
				"$Title":	"[ROOT] GridWave Algorithm (PropDistribution)"
			},
			"GridGen2D.GridWave-b837b252-0a0f-4252-93bc-dd79391e9e31":	{
				"$Position":	{
					"$x":	1604,
					"$y":	159
				}
			},
			"Point3D-92f1f280-232b-447e-ba5f-1e4fb539176a":	{
				"$Position":	{
					"$x":	1703,
					"$y":	-48
				}
			},
			"Single.TileSet.GridWave-b79bb929-b096-4a87-afa0-254269cf7949":	{
				"$Position":	{
					"$x":	2703,
					"$y":	-659
				}
			},
			"Advanced.RuleSet.GridWave-80fda073-db6e-4c18-a539-a0d0e414ddaf":	{
				"$Position":	{
					"$x":	3538,
					"$y":	-921
				}
			},
			"Single.TileSet.GridWave-dc330ec6-9343-455f-b5e8-f7383f50a3dd":	{
				"$Position":	{
					"$x":	2699,
					"$y":	-418
				}
			},
			"Advanced.RuleSet.GridWave-6a4b32f0-5091-400c-bae3-84546c715b01":	{
				"$Position":	{
					"$x":	4099,
					"$y":	-408
				}
			},
			"Single.TileSet.GridWave-36262ef1-a7b1-45a0-ae22-58a5d24276f7":	{
				"$Position":	{
					"$x":	2698,
					"$y":	-165
				}
			},
			"Advanced.RuleSet.GridWave-b54237f7-5ab0-4b24-af1c-0ade66cff3f4":	{
				"$Position":	{
					"$x":	3544,
					"$y":	-124
				}
			},
			"Prop.TileSet.GridWave-4b63bc27-28e4-478e-bbc0-94058954d56e":	{
				"$Position":	{
					"$x":	2379,
					"$y":	4691
				}
			},
			"Union.Prop-1e61d380-0e40-4f03-9d35-ac2d1ce1566a":	{
				"$Position":	{
					"$x":	2389,
					"$y":	4889
				}
			},
			"Prefab.Prop-5a1dbf1f-3b50-4146-915c-8a7db784d841":	{
				"$Position":	{
					"$x":	2399,
					"$y":	5052
				}
			},
			"WeightedPath.Prefab.Prop-ee82d094-3185-4119-8fce-7b144efe4581":	{
				"$Position":	{
					"$x":	2399,
					"$y":	5368
				}
			},
			"Prefab.Prop-4523d305-9457-4f87-9d60-64ca7be9db0d":	{
				"$Position":	{
					"$x":	3188,
					"$y":	5061
				}
			},
			"WeightedPath.Prefab.Prop-584b3acc-2bf5-4cc4-a956-acfbb905dcff":	{
				"$Position":	{
					"$x":	3395,
					"$y":	5365
				}
			},
			"Multi.TileSet.GridWave-47d38c0d-3ea5-404d-972e-c8b1d4ae0bd0":	{
				"$Position":	{
					"$x":	4302,
					"$y":	1337
				}
			},
			"Simple.RuleSet.GridWave-6db69b23-fbd9-4848-9744-7b6aa41270af":	{
				"$Position":	{
					"$x":	5195,
					"$y":	1293
				}
			},
			"Simple.RuleSet.GridWave-307f56b5-d4c9-45fb-9eb4-6e8968cdd733":	{
				"$Position":	{
					"$x":	5192,
					"$y":	1604
				}
			},
			"Single.TileSet.GridWave-f55c094b-bd75-4538-8852-697fa94ba5a0":	{
				"$Position":	{
					"$x":	4702,
					"$y":	1949
				}
			},
			"Simple.RuleSet.GridWave-21e8c890-cac9-4690-9a7c-36464fe64571":	{
				"$Position":	{
					"$x":	5544,
					"$y":	1952
				}
			},
			"Single.TileSet.GridWave-501371d3-0df9-4e4e-b62c-95691ef0c458":	{
				"$Position":	{
					"$x":	4707,
					"$y":	2283
				}
			},
			"Simple.RuleSet.GridWave-7c14992d-679a-437f-93a0-e45bb409c756":	{
				"$Position":	{
					"$x":	5550,
					"$y":	2286
				}
			},
			"Single.TileSet.GridWave-e154908c-3445-43c9-b72f-80ca04332563":	{
				"$Position":	{
					"$x":	4700,
					"$y":	2599
				}
			},
			"Simple.RuleSet.GridWave-f917be4d-1350-4cfb-b928-281dd19f8b65":	{
				"$Position":	{
					"$x":	5543,
					"$y":	2602
				}
			},
			"Prop.TileSet.GridWave-b0597374-b0d9-4a94-89e5-a008f277e920":	{
				"$Position":	{
					"$x":	2447,
					"$y":	2749
				}
			},
			"Simple.RuleSet.GridWave-e13c314f-02a0-49d7-ade6-c964f5f56277":	{
				"$Position":	{
					"$x":	3194,
					"$y":	2729
				}
			},
			"Simple.RuleSet.GridWave-e3efd51b-7049-4931-a658-bdb3cd3fde74":	{
				"$Position":	{
					"$x":	3726,
					"$y":	2750
				}
			},
			"Simple.RuleSet.GridWave-8a030e79-eb58-417e-84e4-c30743151ba0":	{
				"$Position":	{
					"$x":	3197,
					"$y":	3052
				}
			},
			"Simple.RuleSet.GridWave-3302e4a9-521a-487b-8f1d-f0b53ee78313":	{
				"$Position":	{
					"$x":	3734,
					"$y":	3070
				}
			},
			"Union.Prop-6a9e5209-0c90-4b93-943c-c593c1cb0710":	{
				"$Position":	{
					"$x":	2467,
					"$y":	3136
				}
			},
			"Prefab.Prop-3d9ce3eb-6e19-48b0-aa46-532388f37f0e":	{
				"$Position":	{
					"$x":	2461,
					"$y":	3387
				}
			},
			"WeightedPath.Prefab.Prop-d1d1e7a5-5ed7-42b2-aa2b-4725caad61e7":	{
				"$Position":	{
					"$x":	2461,
					"$y":	3703
				}
			},
			"Prefab.Prop-66811315-d9d1-4312-bfda-86190cf40fc2":	{
				"$Position":	{
					"$x":	3250,
					"$y":	3396
				}
			},
			"WeightedPath.Prefab.Prop-75501c38-3428-47a0-8a51-1c94d93f2390":	{
				"$Position":	{
					"$x":	3457,
					"$y":	3700
				}
			},
			"Constant.Seed.GridWave-150a2fbf-b9d0-4a9b-a293-d84e9d8fef96":	{
				"$Position":	{
					"$x":	1691,
					"$y":	841
				}
			},
			"MultiAttempt.Feature.GridWave-6c4f5e0b-4807-4c7b-9b5f-04314552436f":	{
				"$Position":	{
					"$x":	1692,
					"$y":	1007
				}
			},
			"Single.TileSet.GridWave-9b1ec876-2526-4a6e-b65d-d6641ee110d8":	{
				"$Position":	{
					"$x":	2680,
					"$y":	496
				}
			},
			"Advanced.RuleSet.GridWave-59af98ca-9117-45ec-94a6-062194bda4c1":	{
				"$Position":	{
					"$x":	3528,
					"$y":	493
				}
			},
			"Simple.RuleSet.GridWave-812619e0-dd3b-4134-b43d-3a7723a0197f":	{
				"$Position":	{
					"$x":	3119,
					"$y":	4693
				}
			},
			"Single.TileSet.GridWave-d724bca1-89dd-4907-8eed-3bc8eb923d3a":	{
				"$Position":	{
					"$x":	2405,
					"$y":	4059
				}
			},
			"Simple.RuleSet.GridWave-fd6fecc2-6272-49e5-956c-10fdf2978ec7":	{
				"$Position":	{
					"$x":	3250,
					"$y":	4081
				}
			}
		},
		"$FloatingNodes":	[{
				"$NodeId":	"Multi.TileSet.GridWave-47d38c0d-3ea5-404d-972e-c8b1d4ae0bd0",
				"Type":	"Multi",
				"RuleSets":	[{
						"$NodeId":	"Simple.RuleSet.GridWave-6db69b23-fbd9-4848-9744-7b6aa41270af",
						"Type":	"Simple",
						"RuleSet":	{
							"N":	"1,2",
							"E":	"0,00",
							"S":	"1,2",
							"W":	"0,00"
						}
					}, {
						"$NodeId":	"Simple.RuleSet.GridWave-307f56b5-d4c9-45fb-9eb4-6e8968cdd733",
						"Type":	"Simple",
						"RuleSet":	{
							"N":	"1,2",
							"E":	"0,00",
							"S":	"1,2",
							"W":	"0,00"
						}
					}],
				"PrefabPath":	"FancyTiles/Bridges_Small",
				"SizeZ":	1,
				"Weight":	0.8
			}, {
				"$NodeId":	"Single.TileSet.GridWave-f55c094b-bd75-4538-8852-697fa94ba5a0",
				"Type":	"Single",
				"RuleSet":	{
					"$NodeId":	"Simple.RuleSet.GridWave-21e8c890-cac9-4690-9a7c-36464fe64571",
					"Type":	"Simple",
					"RuleSet":	{
						"N":	"1,2",
						"E":	"0,00",
						"S":	"0,00",
						"W":	"1,2"
					}
				},
				"PrefabPath":	"FancyTiles/Canal_Corner",
				"Weight":	1,
				"MinimizeVariants":	true
			}, {
				"$NodeId":	"Single.TileSet.GridWave-501371d3-0df9-4e4e-b62c-95691ef0c458",
				"Type":	"Single",
				"RuleSet":	{
					"$NodeId":	"Simple.RuleSet.GridWave-7c14992d-679a-437f-93a0-e45bb409c756",
					"Type":	"Simple",
					"RuleSet":	{
						"N":	"0,00",
						"E":	"1,2",
						"S":	"0,00",
						"W":	"1,2"
					}
				},
				"Features":	[],
				"PrefabPath":	"FancyTiles/Canal_Straight",
				"Weight":	1,
				"MinimizeVariants":	true
			}, {
				"$NodeId":	"Single.TileSet.GridWave-e154908c-3445-43c9-b72f-80ca04332563",
				"Type":	"Single",
				"RuleSet":	{
					"$NodeId":	"Simple.RuleSet.GridWave-f917be4d-1350-4cfb-b928-281dd19f8b65",
					"Type":	"Simple",
					"RuleSet":	{
						"N":	"1,2",
						"E":	"0,00",
						"S":	"0,00",
						"W":	"0,00"
					}
				},
				"Features":	[],
				"PrefabPath":	"FancyTiles/Canal_Junction",
				"Weight":	1,
				"MinimizeVariants":	true
			}, {
				"$NodeId":	"Single.TileSet.GridWave-d724bca1-89dd-4907-8eed-3bc8eb923d3a",
				"Type":	"Single",
				"RuleSet":	{
					"$NodeId":	"Simple.RuleSet.GridWave-fd6fecc2-6272-49e5-956c-10fdf2978ec7",
					"Type":	"Simple",
					"RuleSet":	{
						"N":	"2",
						"E":	"2",
						"S":	"2",
						"W":	"2"
					}
				},
				"Features":	[],
				"PrefabPath":	"BaseTiles/Foundations/Ruined1x1",
				"Weight":	0.2,
				"MinimizeVariants":	true
			}],
		"$Links":	{
		},
		"$Groups":	[],
		"$Comments":	[],
		"$WorkspaceID":	"HytaleGenerator - PropDistributions"
	}
}